flaskr/__init__.py
flaskr/account.py
flaskr/dashboard.py
teacup_visualization_back-1.0.0.dist-info/LICENSE
teacup_visualization_back-1.0.0.dist-info/METADATA
teacup_visualization_back-1.0.0.dist-info/WHEEL
teacup_visualization_back-1.0.0.dist-info/top_level.txt
teacup_visualization_back-1.0.0.dist-info/RECORD
