Metadata-Version: 2.1
Name: teacup-visualization-back
Version: 1.0.0
Summary: Teacup visualization back-end written in Python
Home-page: https://github.com/HenryssonDaniel/teacup-visualization-web-back-python
Author: Daniel Henrysson
Author-email: henrysson.daniel@gmail.com
License: UNKNOWN
Platform: UNKNOWN
Classifier: Programming Language :: Python :: 3
Classifier: License :: OSI Approved :: MIT License
Classifier: Operating System :: OS Independent
Requires-Dist: flask
Requires-Dist: flask-cors
Requires-Dist: Flask-Session
Requires-Dist: itsdangerous
Requires-Dist: requests
